pydian/__init__.py
pydian/dataframes.py
pydian/dicts.py
pydian/lib/__init__.py
pydian/lib/types.py
pydian/lib/util.py
pydian/mapper.py
pydian/partials.py
pydian/validation/__init__.py
pydian/validation/pydantic.py
pydian/validation/rules.py
pydian/validation/specific.py
pydian/validation/validate.py
pydian-0.4.3.dist-info/LICENSE.md
pydian-0.4.3.dist-info/METADATA
pydian-0.4.3.dist-info/WHEEL
pydian-0.4.3.dist-info/RECORD
